LICENSE
MANIFEST.in
README.rst
setup.py
linkins/__init__.py
linkins/cli.py
linkins/link.py
linkins/script.py
linkins/util.py
linkins.egg-info/PKG-INFO
linkins.egg-info/SOURCES.txt
linkins.egg-info/dependency_links.txt
linkins.egg-info/entry_points.txt
linkins.egg-info/requires.txt
linkins.egg-info/top_level.txt
linkins/test/__init__.py
linkins/test/test_link.py
linkins/test/test_script.py
linkins/test/util.py