Metadata-Version: 1.1
Name: linkins
Version: 0.0.7.4
Summary: Links a directory structure and optionally executes user-defined scripts at each level of the directory hierarchy
Home-page: https://github.com/thelinuxkid/linkins
Author: Andres Buritica
Author-email: andres@thelinuxkid.com
License: MIT
Platform: UNKNOWN
Classifier: Development Status :: 4 - Beta
Classifier: Intended Audience :: Developers
Classifier: Natural Language :: English
Classifier: License :: OSI Approved :: MIT License
Classifier: Programming Language :: Python
Classifier: Programming Language :: Python :: 2.7
